grpc_requests/__init__.py
grpc_requests/aio.py
grpc_requests/client.py
grpc_requests/utils.py
grpc_requests-0.1.21.dist-info/licenses/LICENSE
grpc_requests-0.1.21.dist-info/METADATA
grpc_requests-0.1.21.dist-info/WHEEL
grpc_requests-0.1.21.dist-info/top_level.txt
grpc_requests-0.1.21.dist-info/RECORD
