Metadata-Version: 2.4
Name: grpc_requests
Version: 0.1.21
Summary: grpc for Humans. grpc reflection support client
Home-page: https://github.com/grpc-requests/grpc_requests
Author: wesky93
Author-email: wesky93@gmail.com
Maintainer: ViridianForge
Maintainer-email: wayne@viridianforge.tech
License: Apache License 2.0
Classifier: Intended Audience :: Developers
Classifier: Operating System :: OS Independent
Classifier: Programming Language :: Python
Classifier: Programming Language :: Python :: 3
Classifier: Programming Language :: Python :: 3 :: Only
Classifier: Programming Language :: Python :: 3.9
Classifier: Programming Language :: Python :: 3.10
Classifier: Programming Language :: Python :: 3.11
Classifier: Programming Language :: Python :: 3.12
Classifier: Programming Language :: Python :: 3.13
Classifier: Topic :: Software Development :: Libraries :: Python Modules
Requires-Python: >=3.9
License-File: LICENSE
Requires-Dist: grpcio>=1.60.1
Requires-Dist: grpcio-reflection>=1.60.1
Requires-Dist: protobuf>=4.25.0
Requires-Dist: google-api-core>=2.11.1
Requires-Dist: cryptography>=42.0.8
Dynamic: license-file
Dynamic: requires-dist
